{
  "sample_0": {
    "cfg": {
      "ks": [
        7,
        5,
        3,
        5,
        7,
        3,
        3,
        7,
        7,
        5,
        3,
        3,
        3,
        3,
        5,
        5,
        5,
        7,
        5,
        5
      ],
      "e": [
        4,
        6,
        4,
        3,
        4,
        3,
        6,
        4,
        6,
        6,
        4,
        3,
        4,
        3,
        3,
        6,
        4,
        3,
        3,
        4
      ],
      "d": [
        1,
        1,
        1,
        0,
        0,
        2
      ],
      "image_size": 96,
      "wid": 0
    },
    "corruptions": {
      "Brightness": {
        "5": 79.10669975564734
      },
      "Gaussian Noise": {
        "5": 61.24069480422708
      },
      "Contrast": {
        "5": 52.903225806451616
      },
      "Defocus Blur": {
        "5": 73.1265508552343
      },
      "Elastic": {
        "5": 78.98263028809805
      },
      "Fog": {
        "5": 62.23325062886657
      },
      "Frost": {
        "5": 74.98759307482698
      },
      "Glass Blur": {
        "5": 60.12406948174792
      },
      "Impulse Noise": {
        "5": 60.322580652260605
      },
      "JPEG": {
        "5": 83.44913149850244
      },
      "Motion Blur": {
        "5": 68.6848635046417
      },
      "Pixelate": {
        "5": 85.21091817472472
      },
      "Shot Noise": {
        "5": 63.20099255961757
      },
      "Snow": {
        "5": 66.07940446650124
      },
      "Zoom Blur": {
        "5": 71.48883373364622
      }
    }
  },
  "sample_1": {
    "cfg": {
      "ks": [
        3,
        3,
        3,
        7,
        5,
        5,
        7,
        7,
        5,
        5,
        5,
        5,
        3,
        5,
        3,
        3,
        5,
        5,
        3,
        3
      ],
      "e": [
        4,
        4,
        4,
        6,
        3,
        3,
        4,
        4,
        3,
        4,
        4,
        6,
        4,
        3,
        3,
        3,
        3,
        4,
        4,
        3
      ],
      "d": [
        1,
        2,
        1,
        2,
        0,
        2
      ],
      "image_size": 96,
      "wid": 0
    },
    "corruptions": {
      "Brightness": {
        "5": 77.61786602768058
      },
      "Gaussian Noise": {
        "5": 61.81141440720475
      },
      "Contrast": {
        "5": 52.8287841191067
      },
      "Defocus Blur": {
        "5": 74.21836226962637
      },
      "Elastic": {
        "5": 79.13151370443718
      },
      "Fog": {
        "5": 66.32754343851624
      },
      "Frost": {
        "5": 76.02977669197631
      },
      "Glass Blur": {
        "5": 59.13151364574953
      },
      "Impulse Noise": {
        "5": 61.01736974219234
      },
      "JPEG": {
        "5": 83.37468978843972
      },
      "Motion Blur": {
        "5": 69.82630270681074
      },
      "Pixelate": {
        "5": 85.33498756654801
      },
      "Shot Noise": {
        "5": 65.08684862671656
      },
      "Snow": {
        "5": 68.66004965618882
      },
      "Zoom Blur": {
        "5": 72.03473944841484
      }
    }
  },
  "sample_2": {
    "cfg": {
      "ks": [
        7,
        5,
        3,
        7,
        7,
        7,
        5,
        3,
        5,
        5,
        3,
        3,
        3,
        5,
        3,
        7,
        3,
        3,
        5,
        3
      ],
      "e": [
        4,
        3,
        4,
        6,
        4,
        3,
        4,
        3,
        6,
        4,
        4,
        4,
        3,
        6,
        3,
        4,
        6,
        3,
        6,
        4
      ],
      "d": [
        1,
        2,
        1,
        0,
        0,
        2
      ],
      "image_size": 96,
      "wid": 0
    },
    "corruptions": {
      "Brightness": {
        "5": 77.81637722801038
      },
      "Gaussian Noise": {
        "5": 62.357320114400785
      },
      "Contrast": {
        "5": 52.95285359819237
      },
      "Defocus Blur": {
        "5": 73.52357320477886
      },
      "Elastic": {
        "5": 78.80893299490879
      },
      "Fog": {
        "5": 65.21091812171652
      },
      "Frost": {
        "5": 75.0372208607108
      },
      "Glass Blur": {
        "5": 59.87593052819113
      },
      "Impulse Noise": {
        "5": 61.389578167558014
      },
      "JPEG": {
        "5": 82.8287841039615
      },
      "Motion Blur": {
        "5": 68.58560794044665
      },
      "Pixelate": {
        "5": 84.68982636331033
      },
      "Shot Noise": {
        "5": 64.06947891008174
      },
      "Snow": {
        "5": 67.12158810636838
      },
      "Zoom Blur": {
        "5": 71.63771713862644
      }
    }
  },
  "sample_3": {
    "cfg": {
      "ks": [
        3,
        5,
        3,
        5,
        7,
        3,
        5,
        5,
        7,
        3,
        7,
        5,
        5,
        5,
        7,
        3,
        7,
        5,
        7,
        7
      ],
      "e": [
        4,
        4,
        3,
        3,
        6,
        6,
        6,
        6,
        4,
        3,
        4,
        6,
        4,
        3,
        6,
        4,
        4,
        6,
        4,
        6
      ],
      "d": [
        0,
        2,
        0,
        1,
        0,
        2
      ],
      "image_size": 96,
      "wid": 0
    },
    "corruptions": {
      "Brightness": {
        "5": 77.22084362323467
      },
      "Gaussian Noise": {
        "5": 62.1588089244833
      },
      "Contrast": {
        "5": 52.853598014888334
      },
      "Defocus Blur": {
        "5": 72.25806450855643
      },
      "Elastic": {
        "5": 78.33746894476727
      },
      "Fog": {
        "5": 62.45657568522186
      },
      "Frost": {
        "5": 73.99503723788202
      },
      "Glass Blur": {
        "5": 62.25806453032766
      },
      "Impulse Noise": {
        "5": 61.86104219072214
      },
      "JPEG": {
        "5": 83.44913148714355
      },
      "Motion Blur": {
        "5": 68.95781635823971
      },
      "Pixelate": {
        "5": 85.31017368212527
      },
      "Shot Noise": {
        "5": 64.81389577785141
      },
      "Snow": {
        "5": 66.69975186104219
      },
      "Zoom Blur": {
        "5": 71.16625308848492
      }
    }
  },
  "sample_4": {
    "cfg": {
      "ks": [
        7,
        3,
        5,
        3,
        7,
        7,
        5,
        3,
        3,
        5,
        3,
        3,
        3,
        7,
        3,
        7,
        3,
        3,
        3,
        3
      ],
      "e": [
        4,
        4,
        6,
        6,
        4,
        3,
        6,
        6,
        4,
        6,
        4,
        4,
        3,
        6,
        3,
        6,
        6,
        3,
        3,
        3
      ],
      "d": [
        1,
        0,
        1,
        2,
        0,
        0
      ],
      "image_size": 96,
      "wid": 0
    },
    "corruptions": {
      "Brightness": {
        "5": 77.66749374730415
      },
      "Gaussian Noise": {
        "5": 62.65508684011606
      },
      "Contrast": {
        "5": 52.977667494506456
      },
      "Defocus Blur": {
        "5": 74.11910670353816
      },
      "Elastic": {
        "5": 78.8089329835499
      },
      "Fog": {
        "5": 63.34987592768137
      },
      "Frost": {
        "5": 72.87841192770833
      },
      "Glass Blur": {
        "5": 60.12406949405339
      },
      "Impulse Noise": {
        "5": 61.563275425724
      },
      "JPEG": {
        "5": 83.20099257097647
      },
      "Motion Blur": {
        "5": 68.61042187030499
      },
      "Pixelate": {
        "5": 84.83870970392346
      },
      "Shot Noise": {
        "5": 65.01240695640999
      },
      "Snow": {
        "5": 66.52605461328852
      },
      "Zoom Blur": {
        "5": 72.10918116983646
      }
    }
  },
  "sample_5": {
    "cfg": {
      "ks": [
        7,
        7,
        7,
        5,
        5,
        3,
        3,
        7,
        5,
        3,
        5,
        3,
        5,
        5,
        5,
        7,
        5,
        3,
        3,
        7
      ],
      "e": [
        4,
        3,
        3,
        4,
        6,
        6,
        4,
        6,
        6,
        3,
        3,
        6,
        4,
        3,
        4,
        4,
        4,
        3,
        4,
        3
      ],
      "d": [
        0,
        1,
        1,
        2,
        0,
        0
      ],
      "image_size": 96,
      "wid": 0
    },
    "corruptions": {
      "Brightness": {
        "5": 79.55334982670863
      },
      "Gaussian Noise": {
        "5": 62.40694789365858
      },
      "Contrast": {
        "5": 52.853598014888334
      },
      "Defocus Blur": {
        "5": 73.37468978843972
      },
      "Elastic": {
        "5": 79.13151366278788
      },
      "Fog": {
        "5": 64.54094292993285
      },
      "Frost": {
        "5": 75.70719605817392
      },
      "Glass Blur": {
        "5": 61.76178660996203
      },
      "Impulse Noise": {
        "5": 62.009925573457856
      },
      "JPEG": {
        "5": 83.34987597974299
      },
      "Motion Blur": {
        "5": 69.8014887958839
      },
      "Pixelate": {
        "5": 85.70719602599037
      },
      "Shot Noise": {
        "5": 64.73945409145308
      },
      "Snow": {
        "5": 67.8908188926375
      },
      "Zoom Blur": {
        "5": 72.40694787756681
      }
    }
  },
  "sample_6": {
    "cfg": {
      "ks": [
        7,
        3,
        3,
        7,
        5,
        5,
        7,
        3,
        3,
        5,
        7,
        5,
        7,
        5,
        3,
        5,
        5,
        3,
        3,
        7
      ],
      "e": [
        4,
        4,
        6,
        4,
        4,
        4,
        3,
        4,
        6,
        4,
        3,
        6,
        4,
        4,
        4,
        6,
        6,
        4,
        3,
        4
      ],
      "d": [
        0,
        2,
        2,
        1,
        0,
        0
      ],
      "image_size": 96,
      "wid": 0
    },
    "corruptions": {
      "Brightness": {
        "5": 78.06451618582676
      },
      "Gaussian Noise": {
        "5": 62.28287840339149
      },
      "Contrast": {
        "5": 52.95285359801489
      },
      "Defocus Blur": {
        "5": 74.44168733734055
      },
      "Elastic": {
        "5": 79.67741935862502
      },
      "Fog": {
        "5": 63.0769230684039
      },
      "Frost": {
        "5": 74.66501244102459
      },
      "Glass Blur": {
        "5": 60.74441688054844
      },
      "Impulse Noise": {
        "5": 61.73697270850094
      },
      "JPEG": {
        "5": 83.89578163393082
      },
      "Motion Blur": {
        "5": 70.62034742861765
      },
      "Pixelate": {
        "5": 86.0545906085826
      },
      "Shot Noise": {
        "5": 64.44168734207342
      },
      "Snow": {
        "5": 67.69230772070495
      },
      "Zoom Blur": {
        "5": 73.0272952967187
      }
    }
  },
  "sample_7": {
    "cfg": {
      "ks": [
        7,
        5,
        7,
        3,
        5,
        3,
        7,
        7,
        7,
        3,
        3,
        5,
        5,
        5,
        7,
        5,
        3,
        3,
        3,
        7
      ],
      "e": [
        4,
        6,
        4,
        6,
        4,
        6,
        6,
        4,
        4,
        3,
        6,
        4,
        4,
        4,
        3,
        4,
        4,
        6,
        3,
        6
      ],
      "d": [
        0,
        1,
        1,
        1,
        0,
        1
      ],
      "image_size": 96,
      "wid": 0
    },
    "corruptions": {
      "Brightness": {
        "5": 77.91563274676983
      },
      "Gaussian Noise": {
        "5": 62.158808931109334
      },
      "Contrast": {
        "5": 52.853598014888334
      },
      "Defocus Blur": {
        "5": 74.16873454810964
      },
      "Elastic": {
        "5": 79.03225807966133
      },
      "Fog": {
        "5": 62.25806453127423
      },
      "Frost": {
        "5": 73.27543424885563
      },
      "Glass Blur": {
        "5": 62.43176178376077
      },
      "Impulse Noise": {
        "5": 61.48883374500511
      },
      "JPEG": {
        "5": 83.87096779115738
      },
      "Motion Blur": {
        "5": 70.47146400659906
      },
      "Pixelate": {
        "5": 85.40942934097782
      },
      "Shot Noise": {
        "5": 64.813895778798
      },
      "Snow": {
        "5": 68.53598016592173
      },
      "Zoom Blur": {
        "5": 73.17617868276743
      }
    }
  },
  "sample_8": {
    "cfg": {
      "ks": [
        7,
        3,
        5,
        7,
        7,
        5,
        7,
        7,
        5,
        7,
        3,
        5,
        5,
        7,
        7,
        7,
        5,
        7,
        5,
        7
      ],
      "e": [
        4,
        4,
        3,
        4,
        4,
        6,
        4,
        6,
        6,
        3,
        4,
        4,
        4,
        3,
        4,
        3,
        6,
        4,
        4,
        4
      ],
      "d": [
        0,
        1,
        2,
        1,
        0,
        2
      ],
      "image_size": 96,
      "wid": 0
    },
    "corruptions": {
      "Brightness": {
        "5": 79.2059552857657
      },
      "Gaussian Noise": {
        "5": 62.35732009641586
      },
      "Contrast": {
        "5": 52.92803970223325
      },
      "Defocus Blur": {
        "5": 74.39205954577727
      },
      "Elastic": {
        "5": 78.58560799724115
      },
      "Fog": {
        "5": 63.275434234657006
      },
      "Frost": {
        "5": 74.7642680184717
      },
      "Glass Blur": {
        "5": 62.258064513289305
      },
      "Impulse Noise": {
        "5": 62.13399504668659
      },
      "JPEG": {
        "5": 83.57320097741064
      },
      "Motion Blur": {
        "5": 70.86848638643401
      },
      "Pixelate": {
        "5": 85.88089330782074
      },
      "Shot Noise": {
        "5": 64.66501240410817
      },
      "Snow": {
        "5": 68.0893300361728
      },
      "Zoom Blur": {
        "5": 73.00248141229596
      }
    }
  },
  "sample_9": {
    "cfg": {
      "ks": [
        7,
        5,
        5,
        7,
        5,
        3,
        5,
        7,
        5,
        7,
        5,
        5,
        5,
        3,
        3,
        3,
        7,
        7,
        5,
        7
      ],
      "e": [
        4,
        3,
        3,
        4,
        4,
        4,
        4,
        3,
        4,
        3,
        6,
        4,
        4,
        6,
        6,
        3,
        4,
        4,
        4,
        6
      ],
      "d": [
        1,
        1,
        1,
        0,
        0,
        0
      ],
      "image_size": 96,
      "wid": 0
    },
    "corruptions": {
      "Brightness": {
        "5": 78.66004961453952
      },
      "Gaussian Noise": {
        "5": 62.183622820264944
      },
      "Contrast": {
        "5": 52.80397022332506
      },
      "Defocus Blur": {
        "5": 73.9454094557845
      },
      "Elastic": {
        "5": 79.18114138998405
      },
      "Fog": {
        "5": 63.54838710623994
      },
      "Frost": {
        "5": 74.7394541283695
      },
      "Glass Blur": {
        "5": 61.3647642708298
      },
      "Impulse Noise": {
        "5": 61.488833756364016
      },
      "JPEG": {
        "5": 83.30024818817972
      },
      "Motion Blur": {
        "5": 68.90818859128738
      },
      "Pixelate": {
        "5": 85.50868491274548
      },
      "Shot Noise": {
        "5": 65.06203473661436
      },
      "Snow": {
        "5": 68.16377171783826
      },
      "Zoom Blur": {
        "5": 71.43920594397609
      }
    }
  }
}